frouros/__init__.py
frouros/callbacks/__init__.py
frouros/callbacks/base.py
frouros/callbacks/batch/__init__.py
frouros/callbacks/batch/base.py
frouros/callbacks/batch/permutation_test.py
frouros/callbacks/batch/reset.py
frouros/callbacks/streaming/__init__.py
frouros/callbacks/streaming/base.py
frouros/callbacks/streaming/history.py
frouros/datasets/__init__.py
frouros/datasets/base.py
frouros/datasets/exceptions.py
frouros/datasets/real.py
frouros/datasets/synthetic.py
frouros/detectors/__init__.py
frouros/detectors/base.py
frouros/detectors/concept_drift/__init__.py
frouros/detectors/concept_drift/base.py
frouros/detectors/concept_drift/exceptions.py
frouros/detectors/concept_drift/streaming/__init__.py
frouros/detectors/concept_drift/streaming/base.py
frouros/detectors/concept_drift/streaming/change_detection/__init__.py
frouros/detectors/concept_drift/streaming/change_detection/base.py
frouros/detectors/concept_drift/streaming/change_detection/bocd.py
frouros/detectors/concept_drift/streaming/change_detection/cusum.py
frouros/detectors/concept_drift/streaming/change_detection/geometric_moving_average.py
frouros/detectors/concept_drift/streaming/change_detection/page_hinkley.py
frouros/detectors/concept_drift/streaming/statistical_process_control/__init__.py
frouros/detectors/concept_drift/streaming/statistical_process_control/base.py
frouros/detectors/concept_drift/streaming/statistical_process_control/ddm.py
frouros/detectors/concept_drift/streaming/statistical_process_control/ecdd.py
frouros/detectors/concept_drift/streaming/statistical_process_control/eddm.py
frouros/detectors/concept_drift/streaming/statistical_process_control/hddm.py
frouros/detectors/concept_drift/streaming/statistical_process_control/rddm.py
frouros/detectors/concept_drift/streaming/window_based/__init__.py
frouros/detectors/concept_drift/streaming/window_based/adwin.py
frouros/detectors/concept_drift/streaming/window_based/base.py
frouros-0.9.0.dist-info/LICENSE
frouros-0.9.0.dist-info/METADATA
frouros-0.9.0.dist-info/WHEEL
frouros-0.9.0.dist-info/top_level.txt
frouros-0.9.0.dist-info/RECORD
