Metadata-Version: 2.1
Name: frouros
Version: 0.9.0
Summary: An open-source Python library for drift detection in machine learning systems
Home-page: https://github.com/IFCA-Advanced-Computing/frouros
Author: Jaime Céspedes Sisniega
Author-email: Jaime Céspedes Sisniega <cespedes@ifca.unican.es>
Maintainer: Jaime Céspedes Sisniega
Maintainer-email: Jaime Céspedes Sisniega <cespedes@ifca.unican.es>
License: BSD-3-Clause
Project-URL: homepage, https://frouros.readthedocs.io
Project-URL: repository, https://github.com/IFCA-Advanced-Computing/frouros
Project-URL: documentation, https://frouros.readthedocs.io
Project-URL: download, https://pypi.org/project/frouros/
Keywords: drift-detection,concept-drift,data-drift,machine-learning,data-science,machine-learning-operations,machine-learning-systems
Classifier: Development Status :: 5 - Production/Stable
Classifier: Intended Audience :: Developers
Classifier: Intended Audience :: Science/Research
Classifier: License :: OSI Approved :: BSD License
Classifier: Topic :: Scientific/Engineering
Classifier: Topic :: Scientific/Engineering :: Artificial Intelligence
Classifier: Topic :: Scientific/Engineering :: Mathematics
Classifier: Topic :: Software Development
Classifier: Topic :: Software Development :: Libraries :: Python Modules
Classifier: Programming Language :: Python :: 3.9
Classifier: Programming Language :: Python :: 3.10
Classifier: Programming Language :: Python :: 3.11
Classifier: Programming Language :: Python :: 3.12
Classifier: Programming Language :: Python :: 3 :: Only
Requires-Python: >=3.9,<3.13
License-File: LICENSE
Requires-Dist: matplotlib<3.10,>=3.8.2
Requires-Dist: numpy<2.2,>=1.26.3
Requires-Dist: requests<2.33,>=2.31.0
Requires-Dist: scipy<1.15,>=1.12.0
Requires-Dist: tqdm<5.0,>=4.66.1
Provides-Extra: docs
Requires-Dist: sphinx<8.1,>=7.2.6; extra == "docs"
Requires-Dist: sphinx-book-theme<1.2,>=1.1.0; extra == "docs"
Requires-Dist: sphinxcontrib-bibtex<2.7,>=2.6.2; extra == "docs"
Requires-Dist: myst-parser<4.1,>=2.0.0; extra == "docs"
Requires-Dist: myst-nb<1.2,>=1.0.0; extra == "docs"
Provides-Extra: notebooks
Requires-Dist: scikit-learn<1.6,>=1.3.2; extra == "notebooks"
Requires-Dist: torch<2.5,>=2.1.2; extra == "notebooks"
Requires-Dist: torchvision<0.20,>=0.16.2; extra == "notebooks"
Requires-Dist: ipywidgets<8.2,>=8.1.1; extra == "notebooks"
